{
   "sources" : [
      {
         "usage" : "toplevel",
         "filename" : "iclr2026_conference.tex"
      },
      {
         "usage" : "ignore",
         "filename" : "diagrams/12679_figure_p01.png"
      },
      {
         "usage" : "ignore",
         "filename" : "diagrams/12679_figure_p02.png"
      },
      {
         "usage" : "ignore",
         "filename" : "diagrams/12679_topn_4omini_figure_p01.png"
      },
      {
         "usage" : "ignore",
         "filename" : "diagrams/12679_topn_4omini_figure_p02.png"
      },
      {
         "usage" : "ignore",
         "filename" : "diagrams/16614_figure_p01.png"
      },
      {
         "usage" : "ignore",
         "filename" : "diagrams/16614_figure_p02.png"
      },
      {
         "usage" : "ignore",
         "filename" : "diagrams/16614_figure_p03.png"
      },
      {
         "usage" : "ignore",
         "filename" : "diagrams/16614_figure_pages_anno.pdf"
      },
      {
         "usage" : "ignore",
         "filename" : "diagrams/20112_ata_figure.png"
      },
      {
         "usage" : "ignore",
         "filename" : "diagrams/20112_diver_figure.png"
      },
      {
         "usage" : "ignore",
         "filename" : "diagrams/20112_fine_figure.png"
      },
      {
         "usage" : "ignore",
         "filename" : "diagrams/20112_topn_figure.png"
      },
      {
         "usage" : "ignore",
         "filename" : "diagrams/Buffer_Overflow_Vulnerabilities_subtypes_bar.png"
      },
      {
         "usage" : "ignore",
         "filename" : "diagrams/Memory_Lifecycle_Errors_subtypes_bar.png"
      },
      {
         "usage" : "ignore",
         "filename" : "diagrams/categories_bar.png"
      },
      {
         "usage" : "ignore",
         "filename" : "diagrams/failure_reasons.png"
      },
      {
         "usage" : "ignore",
         "filename" : "diagrams/method_diagram.png"
      },
      {
         "usage" : "ignore",
         "filename" : "iclr2026_conference.bib"
      },
      {
         "usage" : "ignore",
         "filename" : "iclr2026_conference.bst"
      }
   ],
   "spec_version" : 1,
   "texlive_version" : "2025",
   "process" : {
      "compiler" : "pdflatex"
   }
}
